elki_interface/Elki.py
elki_interface/Hics.py
elki_interface/__init__.py
elki_interface/cte.py
elki_interface-0.0.12.dist-info/AUTHORS.rst
elki_interface-0.0.12.dist-info/LICENSE.txt
elki_interface-0.0.12.dist-info/METADATA
elki_interface-0.0.12.dist-info/WHEEL
elki_interface-0.0.12.dist-info/top_level.txt
elki_interface-0.0.12.dist-info/RECORD
