Metadata-Version: 2.1
Name: elki-interface
Version: 0.0.12
Summary: Very basic interface to call elki from python
Home-page: https://github.com/eliavw
Author: Elia vw
Author-email: elia.vw@gmail.com
License: mit
Project-URL: Documentation, https://github.com/eliavw
Platform: any
Classifier: Development Status :: 4 - Beta
Classifier: Programming Language :: Python
Requires-Python: >=3.6
Requires-Dist: numpy
Requires-Dist: scipy
Requires-Dist: pandas
Requires-Dist: prefect
Provides-Extra: testing
Requires-Dist: pytest ; extra == 'testing'
